{
  "root": {
    "type": "root",
    "format": "",
    "indent": 0,
    "version": 1,
    "children": [
      {
        "type": "paragraph",
        "version": 1,
        "direction": "ltr",
        "format": "",
        "indent": 0,
        "children": [
          {
            "type": "text",
            "version": 1,
            "text": "1. Đã uống rượu, bia thì không được lái xe",
            "format": 0,
            "detail": 0,
            "mode": "normal",
            "style": ""
          },
          {
            "type": "text",
            "version": 1,
            "text": "\n",
            "format": 0,
            "detail": 0,
            "mode": "normal",
            "style": ""
          },
          {
            "type": "text",
            "version": 1,
            "text": "Tại Điều 5 của Luật này, có 13 hành vi bị nghiêm cấm trong phòng, chống tác hại của rượu, bia. Trong đó đáng chú ý là hành vi: “Điều khiển phương tiện giao thông mà trong máu hoặc hơi thở có nồng độ cồn”. Như vậy, việc cấm lái xe khi vừa uống rượu, bia đã chính thức được luật hóa.",
            "format": 0,
            "detail": 0,
            "mode": "normal",
            "style": ""
          }
        ]
      },
      {
        "type": "paragraph",
        "version": 1,
        "direction": "ltr",
        "format": "",
        "indent": 0,
        "children": [
          {
            "type": "text",
            "version": 1,
            "text": "",
            "format": 0,
            "detail": 0,
            "mode": "normal",
            "style": ""
          }
        ]
      },
      {
        "type": "paragraph",
        "version": 1,
        "direction": "ltr",
        "format": "",
        "indent": 0,
        "children": [
          {
            "type": "text",
            "version": 1,
            "text": "\n",
            "format": 0,
            "detail": 0,
            "mode": "normal",
            "style": ""
          },
          {
            "type": "text",
            "version": 1,
            "text": "Ngoài ra, Luật cũng nghiêm cấm: Xúi giục, kích động, lôi kéo, ép buộc người khác uống rượu, bia; Người chưa đủ 18 tuổi uống rượu, bia; Quảng cáo rượu có độ cồn từ 15 độ trở lên; Cung cấp thông thông tin không chính xác, sai sự thật về ảnh hưởng của rượu, bia đối với sức khỏe; ",
            "format": 0,
            "detail": 0,
            "mode": "normal",
            "style": ""
          },
          {
            "type": "text",
            "version": 1,
            "text": "Khuyến mại trong hoạt động kinh doanh rượu, bia có độ cồn từ 15 độ trở lên; sử dụng rượu, bia có độ cồn từ 15 độ trở lên để khuyến mại dưới mọi hình thức; Sử dụng nguyên liệu, phụ gia, chất hỗ trợ chế biến không được phép dùng trong thực phẩm; nguyên liệu, phụ gia thực phẩm, chất hỗ trợ chế biến thực phẩm không bảo đảm chất lượng và không rõ nguồn gốc, xuất xứ để sản xuất, pha chế rượu, bia.",
            "format": 0,
            "detail": 0,
            "mode": "normal",
            "style": ""
          },
          {
            "type": "text",
            "version": 1,
            "text": "\n",
            "format": 0,
            "detail": 0,
            "mode": "normal",
            "style": ""
          },
          {
            "type": "text",
            "version": 1,
            "text": "2. Phải dán thông báo không bán rượu, bia cho người dưới 18 tuổi",
            "format": 0,
            "detail": 0,
            "mode": "normal",
            "style": ""
          },
          {
            "type": "text",
            "version": 1,
            "text": "\n",
            "format": 0,
            "detail": 0,
            "mode": "normal",
            "style": ""
          },
          {
            "type": "text",
            "version": 1,
            "text": "Đây là yêu cầu đối với tất cả cơ sở bán rượu, bia. Cụ thể, khoản 5 Điều 32 của Luật chỉ rõ: “Cơ sở bán, rượu, bia phải niêm yết thông báo không bán rượu, bia cho người chưa đủ 18 tuổi",
            "format": 0,
            "detail": 0,
            "mode": "normal",
            "style": ""
          },
          {
            "type": "text",
            "version": 1,
            "text": "”",
            "format": 0,
            "detail": 0,
            "mode": "normal",
            "style": ""
          },
          {
            "type": "text",
            "version": 1,
            "text": ".",
            "format": 0,
            "detail": 0,
            "mode": "normal",
            "style": ""
          },
          {
            "type": "text",
            "version": 1,
            "text": " ",
            "format": 0,
            "detail": 0,
            "mode": "normal",
            "style": ""
          },
          {
            "type": "text",
            "version": 1,
            "text": "Trường hợp nghi ngờ về độ tuổi của người mua rượu, bia thì người bán có quyền yêu cầu người mua xuất trình giấy tờ chứng minh.",
            "format": 0,
            "detail": 0,
            "mode": "normal",
            "style": ""
          },
          {
            "type": "text",
            "version": 1,
            "text": "\n",
            "format": 0,
            "detail": 0,
            "mode": "normal",
            "style": ""
          },
          {
            "type": "text",
            "version": 1,
            "text": "3. Không mở mới điểm bán rượu, bia gần trường học, bệnh viện",
            "format": 0,
            "detail": 0,
            "mode": "normal",
            "style": ""
          },
          {
            "type": "text",
            "version": 1,
            "text": "\n",
            "format": 0,
            "detail": 0,
            "mode": "normal",
            "style": ""
          },
          {
            "type": "text",
            "version": 1,
            "text": "Tại khoản 7, Điều 32 cũng quy định không được mở mới điểm bán rượu, bia để tiêu dùng tại chỗ trong bán kính 100m tính từ khuôn viên của cơ sở y tế, nhà trẻ, trường mẫu giáo, trường mầm non, cơ sở giáo dục phổ thông.",
            "format": 0,
            "detail": 0,
            "mode": "normal",
            "style": ""
          },
          {
            "type": "text",
            "version": 1,
            "text": "\n",
            "format": 0,
            "detail": 0,
            "mode": "normal",
            "style": ""
          },
          {
            "type": "text",
            "version": 1,
            "text": "Điểm bán rượu, bia để tiêu dùng tại chỗ có thể hiểu là các quán bia, nhà hàng có phục vụ rượu",
            "format": 0,
            "detail": 0,
            "mode": "normal",
            "style": ""
          },
          {
            "type": "text",
            "version": 1,
            "text": ", bia",
            "format": 0,
            "detail": 0,
            "mode": "normal",
            "style": ""
          },
          {
            "type": "text",
            "version": 1,
            "text": "…",
            "format": 0,
            "detail": 0,
            "mode": "normal",
            "style": ""
          },
          {
            "type": "text",
            "version": 1,
            "text": "\n",
            "format": 0,
            "detail": 0,
            "mode": "normal",
            "style": ""
          },
          {
            "type": "text",
            "version": 1,
            "text": "4. Thành viên gia đình được hướng dẫn kỹ năng từ chối uống rượu, bia",
            "format": 0,
            "detail": 0,
            "mode": "normal",
            "style": ""
          },
          {
            "type": "text",
            "version": 1,
            "text": "\n",
            "format": 0,
            "detail": 0,
            "mode": "normal",
            "style": ""
          },
          {
            "type": "text",
            "version": 1,
            "text": "Theo Điều 34 của Luật, các gia đình có trách nhiệm giáo dục, giám sát, nhắc nhở thành viên chưa đủ 18 tuổi không uống rượu, bia",
            "format": 0,
            "detail": 0,
            "mode": "normal",
            "style": ""
          },
          {
            "type": "text",
            "version": 1,
            "text": ";",
            "format": 0,
            "detail": 0,
            "mode": "normal",
            "style": ""
          },
          {
            "type": "text",
            "version": 1,
            "text": " các thành viên khác trong gia đình hạn chế uống rượu, bia.",
            "format": 0,
            "detail": 0,
            "mode": "normal",
            "style": ""
          },
          {
            "type": "text",
            "version": 1,
            "text": "\n",
            "format": 0,
            "detail": 0,
            "mode": "normal",
            "style": ""
          },
          {
            "type": "text",
            "version": 1,
            "text": "Đồng thời, cần hướng dẫn các thành viên trong gia đình kỷ năng từ chối uống rượu, bia; kỹ năng nhận biết, ứng xử, xử trí khi gặp người say rượu, bia, người nghiện rượu, bia và các biện pháp phòng, chống tác hại của rượu, bia.",
            "format": 0,
            "detail": 0,
            "mode": "normal",
            "style": ""
          },
          {
            "type": "text",
            "version": 1,
            "text": "\n",
            "format": 0,
            "detail": 0,
            "mode": "normal",
            "style": ""
          },
          {
            "type": "text",
            "version": 1,
            "text": "5. Không quảng cáo rượu, bia dưới 5,5 độ trong khung giờ “vàng”",
            "format": 0,
            "detail": 0,
            "mode": "normal",
            "style": ""
          },
          {
            "type": "text",
            "version": 1,
            "text": "\n",
            "format": 0,
            "detail": 0,
            "mode": "normal",
            "style": ""
          },
          {
            "type": "text",
            "version": 1,
            "text": "Việc quảng cáo đối với rượu có độ cồn từ 15 độ trở lên bị nghiêm cấm. Riêng trong trường hợp quảng cáo rượu, bia có độ cồn dưới 5,5 độ phải tuân thủ các quy định nghiêm ngặt tại khoản 3 Điều 12 của Luật, cụ thể:",
            "format": 0,
            "detail": 0,
            "mode": "normal",
            "style": ""
          },
          {
            "type": "text",
            "version": 1,
            "text": "\n",
            "format": 0,
            "detail": 0,
            "mode": "normal",
            "style": ""
          },
          {
            "type": "text",
            "version": 1,
            "text": "- Không quảng cáo trên truyền hình trong thời gian từ 18 giờ đến 21 giờ hàng ngày, trừ trường hợp quảng cáo có sẵn trong các chương trình thể thao mua bản quyền tiếp sóng trực tiếp từ nước ngoài…",
            "format": 0,
            "detail": 0,
            "mode": "normal",
            "style": ""
          },
          {
            "type": "text",
            "version": 1,
            "text": "\n",
            "format": 0,
            "detail": 0,
            "mode": "normal",
            "style": ""
          },
          {
            "type": "text",
            "version": 1,
            "text": "- Không quảng cáo trên báo nói, trên truyền hình ngay trước, trong và sau chương trình dành cho trẻ em;",
            "format": 0,
            "detail": 0,
            "mode": "normal",
            "style": ""
          },
          {
            "type": "text",
            "version": 1,
            "text": "\n",
            "format": 0,
            "detail": 0,
            "mode": "normal",
            "style": ""
          },
          {
            "type": "text",
            "version": 1,
            "text": "- Không quảng cáo trên phương tiện giao thông…",
            "format": 0,
            "detail": 0,
            "mode": "normal",
            "style": ""
          },
          {
            "type": "text",
            "version": 1,
            "text": "\n",
            "format": 0,
            "detail": 0,
            "mode": "normal",
            "style": ""
          },
          {
            "type": "text",
            "version": 1,
            "text": "Nhằm bảo vệ sức khỏe người dân, phòng chống những nguy cơ bệnh tật và tai nạn nguy hiểm do sử dụng rượu, bia; mọi tổ chức, cá nhân tuân thủ thực hiện các quy định của Luật phòng, chống tác hại của rượu, bia. Hãy hạn chế uống rượu, bia vì không có ngưỡng nào là an toàn cho chúng ta.  ",
            "format": 0,
            "detail": 0,
            "mode": "normal",
            "style": ""
          },
          {
            "type": "text",
            "version": 1,
            "text": "\n",
            "format": 0,
            "detail": 0,
            "mode": "normal",
            "style": ""
          },
          {
            "type": "text",
            "version": 1,
            "text": "                                                                                                                                        Hữu Quý",
            "format": 0,
            "detail": 0,
            "mode": "normal",
            "style": ""
          },
          {
            "type": "text",
            "version": 1,
            "text": "\n",
            "format": 0,
            "detail": 0,
            "mode": "normal",
            "style": ""
          }
        ]
      }
    ]
  }
}